donodo/__init__.py
donodo/config.py
donodo/docker.py
donodo/templates.py
donodo/zenodo.py
donodo-0.4.dist-info/licenses/LICENSE
donodo-0.4.dist-info/METADATA
donodo-0.4.dist-info/WHEEL
donodo-0.4.dist-info/entry_points.txt
donodo-0.4.dist-info/top_level.txt
donodo-0.4.dist-info/RECORD
