Metadata-Version: 2.4
Name: donodo
Version: 0.4
Summary: Bridging Docker images with Zenodo
Home-page: https://github.com/pauleve/donodo
Author: Loïc Paulevé
Author-email: loic.pauleve@labri.fr
License: MIT
License-File: LICENSE
Requires-Dist: requests
Dynamic: author
Dynamic: author-email
Dynamic: home-page
Dynamic: license
Dynamic: license-file
Dynamic: requires-dist
Dynamic: summary
